{
  "May 3 2025": [
    { "name": "Abayan", "status": "Late" },
    { "name": "Adiarte", "status": "Present" },
    { "name": "Fabros", "status": "Absent" },
    { "name": "Caridad", "status": "Late" },
    { "name": "Eja", "status": "Present" },
    { "name": "Escaraman", "status": "Present" },
    { "name": "Amis", "status": "Absent" },
    { "name": "Joreen", "status": "Absent" },
    { "name": "Ruben", "status": "Absent" },
    { "name": "Afliccion", "status": "Present" }
  ],
  "May 4 2025": [
    { "name": "Abayan", "status": "Late" },
    { "name": "Adiarte", "status": "Present" },
    { "name": "Fabros", "status": "Absent" },
    { "name": "Caridad", "status": "Late" },
    { "name": "Eja", "status": "Present" },
    { "name": "Escaraman", "status": "Present" },
    { "name": "Amis", "status": "Absent" },
    { "name": "Joreen", "status": "Absent" },
    { "name": "Ruben", "status": "Absent" },
    { "name": "Afliccion", "status": "Present" }
  ],
  "May 5 2025": [
    { "name": "Abayan", "status": "Late" },
    { "name": "Adiarte", "status": "Present" },
    { "name": "Fabros", "status": "Absent" },
    { "name": "Caridad", "status": "Late" },
    { "name": "Eja", "status": "Present" },
    { "name": "Escaraman", "status": "Present" },
    { "name": "Amis", "status": "Absent" },
    { "name": "Joreen", "status": "Absent" },
    { "name": "Ruben", "status": "Absent" },
    { "name": "Afliccion", "status": "Present" }
  ],
  "May 6 2025": [
    { "name": "Abayan", "status": "Late" },
    { "name": "Adiarte", "status": "Present" },
    { "name": "Fabros", "status": "Absent" },
    { "name": "Caridad", "status": "Late" },
    { "name": "Eja", "status": "Present" },
    { "name": "Escaraman", "status": "Present" },
    { "name": "Amis", "status": "Absent" },
    { "name": "Joreen", "status": "Absent" },
    { "name": "Ruben", "status": "Absent" },
    { "name": "Afliccion", "status": "Present" }
  ],
  "May 7 2025": [
    { "name": "Abayan", "status": "Late" },
    { "name": "Adiarte", "status": "Late" },
    { "name": "Fabros", "status": "Present" },
    { "name": "Caridad", "status": "Late" },
    { "name": "Eja", "status": "Present" },
    { "name": "Escaraman", "status": "Present" },
    { "name": "Amis", "status": "Present" },
    { "name": "Joreen", "status": "Present" },
    { "name": "Ruben", "status": "Present" },
    { "name": "Afliccion", "status": "Present" }
  ],
  "May 8 2025": [
    { "name": "Abayan", "status": "Present" },
    { "name": "Adiarte", "status": "Late" },
    { "name": "Fabros", "status": "Present" },
    { "name": "Caridad", "status": "Present" },
    { "name": "Eja", "status": "Present" },
    { "name": "Escaraman", "status": "Late" },
    { "name": "Amis", "status": "Present" },
    { "name": "Joreen", "status": "Absent" },
    { "name": "Ruben", "status": "Present" },
    { "name": "Afliccion", "status": "Present" }
  ],
  "May 9 2025": [
    { "name": "Abayan", "status": "Present" },
    { "name": "Adiarte", "status": "Present" },
    { "name": "Fabros", "status": "Absent" },
    { "name": "Caridad", "status": "Present" },
    { "name": "Eja", "status": "Present" },
    { "name": "Escaraman", "status": "Present" },
    { "name": "Amis", "status": "Present" },
    { "name": "Joreen", "status": "Present" },
    { "name": "Ruben", "status": "Present" },
    { "name": "Afliccion", "status": "Present" }
  ],
  "May 10 2025": [
    { "name": "Abayan", "status": "Late" },
    { "name": "Adiarte", "status": "Present" },
    { "name": "Fabros", "status": "Present" },
    { "name": "Caridad", "status": "Late" },
    { "name": "Eja", "status": "Present" },
    { "name": "Escaraman", "status": "Present" },
    { "name": "Amis", "status": "Absent" },
    { "name": "Joreen", "status": "Present" },
    { "name": "Ruben", "status": "Present" },
    { "name": "Afliccion", "status": "Absent" }
  ]
}
